README.md
setup.py
ozark/__init__.py
ozark/__main__.py
ozark/cli.py
ozark/lambda_handler.py
ozark/ozark_handler.py
ozark/utils.py
ozark.egg-info/PKG-INFO
ozark.egg-info/SOURCES.txt
ozark.egg-info/dependency_links.txt
ozark.egg-info/entry_points.txt
ozark.egg-info/requires.txt
ozark.egg-info/top_level.txt