Metadata-Version: 1.0
Name: ozark
Version: 0.0
Summary: Ozark deploys your Python scripts on Lambda.
Home-page: https://github.com/bertrandchenal/ozark
Author: Bertrand Chenal
Author-email: UNKNOWN
License: MIT
Platform: UNKNOWN
